renspell/__init__.py
renspell/main.py
renspell/parse.py
renspell-0.2.2.dist-info/entry_points.txt
renspell-0.2.2.dist-info/LICENSE
renspell-0.2.2.dist-info/WHEEL
renspell-0.2.2.dist-info/METADATA
renspell-0.2.2.dist-info/RECORD
