Metadata-Version: 2.1
Name: renspell
Version: 0.2.2
Summary: A spell-checker for Ren'Py scripts
Home-page: https://gitlab.com/hlieberman/renspell
License: GPL-3.0-only
Keywords: renpy,ren'py,spellcheck,grammar
Author: Harlan Lieberman-Berg
Author-email: hlieberman@setec.io
Requires-Python: >=3.8,<4.0
Classifier: Development Status :: 4 - Beta
Classifier: Environment :: Console
Classifier: License :: OSI Approved :: GNU General Public License v3 (GPLv3)
Classifier: Programming Language :: Python :: 3
Classifier: Programming Language :: Python :: 3.8
Classifier: Programming Language :: Python :: 3.9
Classifier: Topic :: Artistic Software
Classifier: Topic :: Games/Entertainment :: Role-Playing
Requires-Dist: click (>=7.1.2,<8.0.0)
Requires-Dist: colorama (>=0.4.4,<0.5.0)
Requires-Dist: language-tool-python (>=2.4.7,<3.0.0)
Project-URL: Repository, https://gitlab.com/hlieberman/renspell.git
